hop/__about__.py
hop/__init__.py
hop/__main__.py
hop/app.py
hop/hop_functions.py
hop/icons.py
hop_file_browser-2.1.0.dist-info/METADATA
hop_file_browser-2.1.0.dist-info/WHEEL
hop_file_browser-2.1.0.dist-info/entry_points.txt
hop_file_browser-2.1.0.dist-info/licenses/LICENSE
hop_file_browser-2.1.0.dist-info/RECORD
