Metadata-Version: 2.1
Name: hop-file-browser
Version: 2.1.0
Summary: An intuitive and fast terminal file browser
Project-URL: Documentation, https://github.com/benrutter/hop#readme
Project-URL: Issues, https://github.com/benrutter/hop/issues
Project-URL: Source, https://github.com/benrutter/hop
License-File: LICENSE
Classifier: Development Status :: 4 - Beta
Classifier: Programming Language :: Python
Classifier: Programming Language :: Python :: 3.7
Classifier: Programming Language :: Python :: 3.8
Classifier: Programming Language :: Python :: 3.9
Classifier: Programming Language :: Python :: 3.10
Classifier: Programming Language :: Python :: 3.11
Classifier: Programming Language :: Python :: Implementation :: CPython
Classifier: Programming Language :: Python :: Implementation :: PyPy
Requires-Python: >=3.6
Requires-Dist: rich
Requires-Dist: send2trash
Provides-Extra: unix
Requires-Dist: getch; extra == 'unix'
